emacs_sway_xkb/__init__.py
emacs_sway_xkb/emacs_sway_xkb.py
sway_xkb_switcher/__init__.py
sway_xkb_switcher/switcher.py
sway_xkb_switcher-0.3.0.dist-info/entry_points.txt
sway_xkb_switcher-0.3.0.dist-info/LICENSE
sway_xkb_switcher-0.3.0.dist-info/WHEEL
sway_xkb_switcher-0.3.0.dist-info/METADATA
sway_xkb_switcher-0.3.0.dist-info/RECORD
