Metadata-Version: 2.1
Name: sway-xkb-switcher
Version: 0.3.0
Summary: Keyboard layout switcher for sway windows
Home-page: https://github.com/nmukhachev/sway-xkb-switcher
License: MIT
Author: Innokenty Lebedev
Maintainer: Nikolay Mukhachev
Requires-Python: >=3.8,<4.0
Classifier: License :: OSI Approved :: MIT License
Classifier: Programming Language :: Python :: 3
Classifier: Programming Language :: Python :: 3.8
Classifier: Programming Language :: Python :: 3.9
Requires-Dist: i3ipc (>=2.1.1,<3.0.0)
Project-URL: Repository, https://github.com/nmukhachev/sway-xkb-switcher
